cognee_community_vector_adapter_weaviate/__init__.py
cognee_community_vector_adapter_weaviate/register.py
cognee_community_vector_adapter_weaviate/weaviate_adapter.py
cognee_community_vector_adapter_weaviate-0.0.2.dist-info/METADATA
cognee_community_vector_adapter_weaviate-0.0.2.dist-info/WHEEL
cognee_community_vector_adapter_weaviate-0.0.2.dist-info/RECORD
