Metadata-Version: 2.3
Name: cognee-community-vector-adapter-weaviate
Version: 0.0.2
Summary: Weaviate vector database adapter for cognee
Requires-Python: >=3.11,<=3.13
Classifier: Programming Language :: Python :: 3
Classifier: Programming Language :: Python :: 3.11
Classifier: Programming Language :: Python :: 3.12
Classifier: Programming Language :: Python :: 3.13
Requires-Dist: cognee (>=0.2.4)
Requires-Dist: weaviate-client (>=4.9.6,<5.0.0)
